sentry_qyweixin/__init__.py
sentry_qyweixin/forms.py
sentry_qyweixin/plugin.py
cbs_sentry_qyweixin-1.0.1.dist-info/LICENSE
cbs_sentry_qyweixin-1.0.1.dist-info/METADATA
cbs_sentry_qyweixin-1.0.1.dist-info/WHEEL
cbs_sentry_qyweixin-1.0.1.dist-info/entry_points.txt
cbs_sentry_qyweixin-1.0.1.dist-info/top_level.txt
cbs_sentry_qyweixin-1.0.1.dist-info/RECORD
