Metadata-Version: 2.1
Name: cbs-sentry-qyweixin
Version: 1.0.1
Summary: A Sentry extension which send errors stats to DingDing Fix#22
Home-page: https://github.com/anshengme/sentry-dingding
Author: ansheng
Author-email: ianshengme@gmail.com
License: MIT
Keywords: sentry qyweixin
Classifier: Programming Language :: Python :: 2.7
Classifier: License :: OSI Approved :: MIT License
License-File: LICENSE
Requires-Dist: sentry >=9.0.0
Requires-Dist: requests
